{
  "uuid": "ieFx",
  "titre": "",
  "theme": "",
  "niveau": "",
  "metadata": {
    "exo7id": "1637",
    "auteur": "barraud",
    "createdAt": "2003-09-01",
    "hasIndication": "false",
    "hasCorrection": "false",
    "chapitre": "Réduction d'endomorphisme, polynôme annulateur",
    "sousChapitre": "Diagonalisation",
    "organisation": "exo7",
    "updatedAt": "2025-03-04T15:16:15.465Z"
  },
  "contenu": [
    {
      "id": "655c2142-cbb2-4a42-b980-b33aa96aa9e7",
      "type": "description",
      "value": {
        "latex": "On considère une matrice $A\\in\\mathcal{M}_{nn}(\\C)$ et l'application $\\phi_{A}$\n  définie par~:\n  $$\n  \\phi_{A}:\n  \\begin{array}{ccc}\n    \\mathcal{M}_{nn}(\\C) & \\rightarrow & \\mathcal{M}_{nn}(\\C)\\\\\n    B           &\\mapsto &AB\n  \\end{array}\n  $$",
        "html": "<p>On considère une matrice <span\nclass=\"math inline\">\\(A\\in\\mathcal{M}_{nn}(\\C)\\)</span> et l’application\n<span class=\"math inline\">\\(\\phi_{A}\\)</span> définie par : <span\nclass=\"math display\">\\[\\phi_{A}:\n  \\begin{array}{ccc}\n    \\mathcal{M}_{nn}(\\C) &amp; \\rightarrow &amp; \\mathcal{M}_{nn}(\\C)\\\\\n    B           &amp;\\mapsto &amp;AB\n  \\end{array}\\]</span></p>\n"
      }
    },
    {
      "id": "b3992716-c050-4e8e-a1df-9a3f896682f3",
      "type": "question",
      "value": {
        "latex": "Montrer que $\\phi_{A}$ est linéaire.\n\n    Le but de l'exercice est de montrer que $\\phi_{A}$ est diagonalisable\n    si et seulement si $A$ est diagonalisable.",
        "html": "<p>Montrer que <span class=\"math inline\">\\(\\phi_{A}\\)</span> est\nlinéaire.</p>\n<p>Le but de l’exercice est de montrer que <span\nclass=\"math inline\">\\(\\phi_{A}\\)</span> est diagonalisable si et\nseulement si <span class=\"math inline\">\\(A\\)</span> est\ndiagonalisable.</p>\n"
      }
    },
    {
      "id": "14963450-9841-432c-8f24-3370e439086d",
      "type": "question",
      "value": {
        "latex": "Calculer $\\phi_{A}^{2}(B)$, puis $\\phi_{A}^{k}(B)$ pour $k\\in\\N$. En\n    déduire que si $P$ est un polynôme, alors $P(\\phi_{A})=\\phi_{P(A)}$.",
        "html": "<p>Calculer <span class=\"math inline\">\\(\\phi_{A}^{2}(B)\\)</span>, puis\n<span class=\"math inline\">\\(\\phi_{A}^{k}(B)\\)</span> pour <span\nclass=\"math inline\">\\(k\\in\\N\\)</span>. En déduire que si <span\nclass=\"math inline\">\\(P\\)</span> est un polynôme, alors <span\nclass=\"math inline\">\\(P(\\phi_{A})=\\phi_{P(A)}\\)</span>.</p>\n"
      }
    },
    {
      "id": "0f5e2861-82e5-4fab-b23e-ef6d9b9376db",
      "type": "question",
      "value": {
        "latex": "En déduire que $P$ est un polynôme annulateur de $A$ si et seulement\n    si $P$ est un polynôme annulateur de $\\phi_{A}$.",
        "html": "<p>En déduire que <span class=\"math inline\">\\(P\\)</span> est un polynôme\nannulateur de <span class=\"math inline\">\\(A\\)</span> si et seulement si\n<span class=\"math inline\">\\(P\\)</span> est un polynôme annulateur de\n<span class=\"math inline\">\\(\\phi_{A}\\)</span>.</p>\n"
      }
    },
    {
      "id": "805807f6-dcca-44e3-8d73-804ddbd0497c",
      "type": "question",
      "value": {
        "latex": "Montrer que $\\phi_{A}$ est diagonalisable si et seulement si $A$\n    l'est.",
        "html": "<p>Montrer que <span class=\"math inline\">\\(\\phi_{A}\\)</span> est\ndiagonalisable si et seulement si <span class=\"math inline\">\\(A\\)</span>\nl’est.</p>\n"
      }
    }
  ],
  "preview": "<p>On considère une matrice <span\nclass=\"math inline\">\\(A\\in\\mathcal{M}_{nn}(\\C)\\)</span> et l’application\n<span class=\"math inline\">\\(\\phi_{A}\\)</spa ..."
}