{
  "uuid": "iuIu",
  "titre": "",
  "theme": "",
  "niveau": "",
  "metadata": {
    "exo7id": "1618",
    "auteur": "liousse",
    "createdAt": "2003-10-01",
    "hasIndication": "false",
    "hasCorrection": "false",
    "chapitre": "Réduction d'endomorphisme, polynôme annulateur",
    "sousChapitre": "Diagonalisation",
    "organisation": "exo7",
    "updatedAt": "2025-02-13T07:43:53.276Z"
  },
  "contenu": [
    {
      "id": "fcbcb5ba-67fc-44b3-92f8-53db193e7665",
      "type": "description",
      "value": {
        "latex": "On consid\\`ere les matrices suivantes\n$$A=\\left (\\begin{array}{ccc}\n3&1&1\\\\2&4&2\\\\1&1&3\\end{array}\\right )\\hbox{  }\nB=\\left (\\begin{array}{ccc}\n1&2&2\\\\1&2&-1\\\\-1&1&4\\end{array}\\right )\\hbox{  }\nC=\\left (\\begin{array}{ccc}\n1&1&0\\\\0&1&0\\\\0&0&1\\end{array}\\right )$$ \nCes matrices sont-elles diagonalisables ? Si oui, les r\\'eduire.",
        "html": "<p>On considère les matrices suivantes <span class=\"math display\">\\[A=\\left (\\begin{array}{ccc}\n3&amp;1&amp;1\\\\2&amp;4&amp;2\\\\1&amp;1&amp;3\\end{array}\\right )\\hbox{  }\nB=\\left (\\begin{array}{ccc}\n1&amp;2&amp;2\\\\1&amp;2&amp;-1\\\\-1&amp;1&amp;4\\end{array}\\right )\\hbox{  }\nC=\\left (\\begin{array}{ccc}\n1&amp;1&amp;0\\\\0&amp;1&amp;0\\\\0&amp;0&amp;1\\end{array}\\right )\\]</span> Ces matrices sont-elles diagonalisables ? Si oui, les réduire.</p>\n"
      }
    }
  ],
  "preview": "<p>On considère les matrices suivantes <span class=\"math display\"> ..."
}