{
  "uuid": "rJjM",
  "titre": "",
  "theme": "",
  "niveau": "",
  "metadata": {
    "exo7id": "3509",
    "auteur": "quercia",
    "createdAt": "2010-03-10",
    "hasIndication": "false",
    "hasCorrection": "false",
    "chapitre": "Réduction d'endomorphisme, polynôme annulateur",
    "sousChapitre": "Valeur propre, vecteur propre",
    "organisation": "exo7",
    "updatedAt": "2025-02-13T07:44:07.150Z"
  },
  "contenu": [
    {
      "id": "8e90e399-8910-432c-af63-8b4900419f80",
      "type": "description",
      "value": {
        "latex": "Soit $M=(m_{ij}) \\in \\mathcal{M}_n(\\R)$ telle que :\n$\\begin{cases} \\forall\\ i,j,\\ m_{ij} \\ge 0 \\cr\n         \\forall\\ i,\\ m_{i,1} + m_{i,2} + \\dots + m_{i,n} = 1.\\cr \\end{cases}$\n({\\it matrice stochastique\\/})",
        "html": "<p>Soit <span class=\"math inline\">\\(M=(m_{ij}) \\in \\mathcal{M}_n(\\R)\\)</span> telle que : <span class=\"math inline\">\\(\\begin{cases} \\forall\\ i,j,\\ m_{ij} \\ge 0 \\cr\n         \\forall\\ i,\\ m_{i,1} + m_{i,2} + \\dots + m_{i,n} = 1.\\cr \\end{cases}\\)</span> (<span><em>matrice stochastique</em></span>)</p>\n"
      }
    },
    {
      "id": "aef34b77-ddce-4818-b14e-8baa77d85b0d",
      "type": "question",
      "value": {
        "latex": "Montrer que 1 est valeur propre de $M$.",
        "html": "<p>Montrer que 1 est valeur propre de <span class=\"math inline\">\\(M\\)</span>.</p>\n"
      }
    },
    {
      "id": "3b4f0605-bb8d-40c8-b297-61d736bf2792",
      "type": "question",
      "value": {
        "latex": "Soit $\\lambda$ une valeur propre complexe de $M$.\n    Montrer que $|\\lambda| \\le 1$\n    (si $(x_1,\\dots,x_n)\\in \\C^n$ est un vecteur propre associé, considérer le\n    coefficient $x_k$ de plus grand module).\n    Montrer que si tous les\n    coefficients $m_{ij}$ sont strictement positifs alors $|\\lambda| = 1  \\Rightarrow  \\lambda = 1$.",
        "html": "<p>Soit <span class=\"math inline\">\\(\\lambda\\)</span> une valeur propre complexe de <span class=\"math inline\">\\(M\\)</span>. Montrer que <span class=\"math inline\">\\(|\\lambda| \\le 1\\)</span> (si <span class=\"math inline\">\\((x_1,\\dots,x_n)\\in \\C^n\\)</span> est un vecteur propre associé, considérer le coefficient <span class=\"math inline\">\\(x_k\\)</span> de plus grand module). Montrer que si tous les coefficients <span class=\"math inline\">\\(m_{ij}\\)</span> sont strictement positifs alors <span class=\"math inline\">\\(|\\lambda| = 1  \\Rightarrow  \\lambda = 1\\)</span>.</p>\n"
      }
    }
  ],
  "preview": "<p>Soit <span class=\"math inline\">\\(M=(m_{ij}) \\in \\mathcal{M}_n(\\R)\\)</span> telle que : <span class=\"math inline\"> ..."
}