{
  "uuid": "7IYD",
  "titre": "",
  "theme": "",
  "niveau": "",
  "metadata": {
    "exo7id": "7540",
    "auteur": "mourougane",
    "createdAt": "2021-08-10",
    "hasIndication": "false",
    "hasCorrection": "false",
    "chapitre": "Fonction holomorphe",
    "sousChapitre": "Fonction holomorphe",
    "organisation": "exo7",
    "updatedAt": "2025-02-13T07:40:18.205Z"
  },
  "contenu": [
    {
      "id": "ae8eed22-7648-420c-8bc8-5bde27c86ef2",
      "type": "description",
      "value": {
        "latex": "On rappelle que $\\Delta:=\\{z\\in\\Cc / |z|<1\\}$, $\\mathbb{H}:=\\{z\\in\\Cc / Im(z)>0\\}$ et $\\Cc^-:=\\Cc-\\{z\\in\\Cc / Im(z)=0 \\quad \\text{ et } \\quad Re(z)\\leq 0\\}$.",
        "html": "<p>On rappelle que <span class=\"math inline\">\\(\\Delta:=\\{z\\in\\Cc / |z|&lt;1\\}\\)</span>, <span class=\"math inline\">\\(\\mathbb{H}:=\\{z\\in\\Cc / Im(z)&gt;0\\}\\)</span> et <span class=\"math inline\">\\(\\Cc^-:=\\Cc-\\{z\\in\\Cc / Im(z)=0 \\quad \\text{ et } \\quad Re(z)\\leq 0\\}\\)</span>.</p>\n"
      }
    },
    {
      "id": "4467c99c-a2d3-4b92-bacf-0745d030f9f1",
      "type": "question",
      "value": {
        "latex": "Montrer que l'application \r\n$$\\begin{array}{cccc}\r\n q:& \\mathbb{H}&\\longrightarrow&\\Cc^{-}\\\\&z&\\longmapsto& -z^2\r\n\\end{array}$$\r\nest holomorphe et bijective.",
        "html": "<p>Montrer que l’application <span class=\"math display\">\\[\\begin{array}{cccc}\n q:&amp; \\mathbb{H}&amp;\\longrightarrow&amp;\\Cc^{-}\\\\&amp;z&amp;\\longmapsto&amp; -z^2\n\\end{array}\\]</span> est holomorphe et bijective.</p>\n"
      }
    },
    {
      "id": "a09e0d4f-ab2d-4b51-b97c-b7943646a011",
      "type": "question",
      "value": {
        "latex": "En déduire une application holomorphe et bijective de $\\Delta$ sur $\\Cc^-$.",
        "html": "<p>En déduire une application holomorphe et bijective de <span class=\"math inline\">\\(\\Delta\\)</span> sur <span class=\"math inline\">\\(\\Cc^-\\)</span>.</p>\n"
      }
    }
  ],
  "preview": "<p>On rappelle que <span class=\"math inline\">\\(\\Delta:=\\{z\\in\\Cc / |z|&lt;1\\}\\)</span>, <span class=\"math inline\"> ..."
}