{
  "uuid": "blLe",
  "titre": "",
  "theme": "",
  "niveau": "",
  "metadata": {
    "exo7id": "2873",
    "auteur": "burnol",
    "createdAt": "2009-12-15",
    "hasIndication": "false",
    "hasCorrection": "false",
    "chapitre": "Autre",
    "sousChapitre": "Autre",
    "organisation": "exo7",
    "updatedAt": "2025-02-13T07:40:38.744Z"
  },
  "contenu": [
    {
      "id": "1dc2f2a4-4943-44cb-8e2c-7973a39565c5",
      "type": "description",
      "value": {
        "latex": "\\'Etant admis que \n$\\sin(\\pi z) = \\pi z \\prod_{k=1}^\\infty \\left(1 -\n  \\frac{z^2}{k^2}\\right)$, \nprouver:\n\\[ \\sin(\\pi z) = \\pi z \\prod_{\\substack{k=-\\infty \\\\ k\\neq0}}^{+\\infty} \\left(1 -\n  \\frac{z}{k}\\right)e^{\\frac zk} \\]\net justifier la convergence absolue du produit.",
        "html": "<p>Étant admis que <span class=\"math inline\">\\(\\sin(\\pi z) = \\pi z \\prod_{k=1}^\\infty \\left(1 -\n  \\frac{z^2}{k^2}\\right)\\)</span>, prouver: <span class=\"math display\">\\[\\sin(\\pi z) = \\pi z \\prod_{\\substack{k=-\\infty \\\\ k\\neq0}}^{+\\infty} \\left(1 -\n  \\frac{z}{k}\\right)e^{\\frac zk}\\]</span> et justifier la convergence absolue du produit.</p>\n"
      }
    }
  ],
  "preview": "<p>Étant admis que <span class=\"math inline\">\\(\\sin(\\pi z) = \\pi z \\prod_{k=1}^\\infty \\left(1 -\n  \\frac{z^2}{k^2}\\right)\\)</span>, prouver: <span clas ..."
}