{
  "uuid": "oJOB",
  "titre": "",
  "theme": "",
  "niveau": "",
  "metadata": {
    "exo7id": "6203",
    "auteur": "queffelec",
    "createdAt": "2011-10-16",
    "hasIndication": "false",
    "hasCorrection": "false",
    "chapitre": "Compacité",
    "sousChapitre": "Compacité",
    "organisation": "exo7",
    "updatedAt": "2025-02-13T07:40:09.678Z"
  },
  "contenu": [
    {
      "id": "43f949eb-5bdf-47aa-b66c-acb73c5cd731",
      "type": "description",
      "value": {
        "latex": "Soit $(A_n)$ une suite décroissante de compacts connexes non vides dans un\nespace topologique séparé. Montrer que $\\cap_n A_n$ est encore un compact\nconnexe non vide. (Pour la connexité on pourra raisonner avec de fermés et\nutiliser l'exercice \\ref{exn11}.)",
        "html": "<p>Soit <span class=\"math inline\">\\((A_n)\\)</span> une suite décroissante de compacts connexes non vides dans un espace topologique séparé. Montrer que <span class=\"math inline\">\\(\\cap_n A_n\\)</span> est encore un compact connexe non vide. (Pour la connexité on pourra raisonner avec de fermés et utiliser l’exercice <a href=\"#exn11\" data-reference-type=\"ref\" data-reference=\"exn11\">[exn11]</a>.)</p>\n"
      }
    }
  ],
  "preview": "<p>Soit <span class=\"math inline\">\\((A_n)\\)</span> une suite décroissante de compacts connexes non vides dans un espace topologique séparé. Montrer qu ..."
}