{
  "uuid": "9Z4L",
  "titre": "",
  "theme": "",
  "niveau": "",
  "metadata": {
    "exo7id": "1239",
    "auteur": "ridde",
    "createdAt": "1999-11-01",
    "hasIndication": "false",
    "hasCorrection": "true",
    "chapitre": "Développement limité",
    "sousChapitre": "Calculs",
    "organisation": "exo7",
    "updatedAt": "2025-02-13T07:41:18.592Z"
  },
  "contenu": [
    {
      "id": "cfaaaebc-ffe3-479f-bf6a-023a2a84b824",
      "type": "description",
      "value": {
        "latex": "D\\'eterminer la limite en $0$ de $\\dfrac{\\arctan x\n- \\sin x}{\\tan x - \\arcsin x}$.",
        "html": "<p>Déterminer la limite en <span class=\"math inline\">\\(0\\)</span> de <span class=\"math inline\">\\(\\dfrac{\\arctan x\n- \\sin x}{\\tan x - \\arcsin x}\\)</span>.</p>\n"
      }
    },
    {
      "id": "9f27f74b-ebd4-49c5-aa23-4e564f08a1e2",
      "type": "reponse",
      "value": {
        "latex": "$$\\lim _{x\\rightarrow 0}{\\frac {\\arctan(x)-\\sin(x)}{\\tan(x)-\\arcsin(x)}}\n=-1.$$",
        "html": "<p><span class=\"math display\">\\[\\lim _{x\\rightarrow 0}{\\frac {\\arctan(x)-\\sin(x)}{\\tan(x)-\\arcsin(x)}}\n=-1.\\]</span></p>\n"
      }
    }
  ],
  "preview": "<p>Déterminer la limite en <span class=\"math inline\">\\(0\\)</span> de <span class=\"math inline\">\\(\\dfrac{\\arctan x\n- \\sin x}{\\tan x - \\arcsin x}\\)</spa ..."
}