{
  "uuid": "LTv9",
  "titre": "",
  "theme": "",
  "niveau": "",
  "metadata": {
    "exo7id": "4301",
    "auteur": "quercia",
    "createdAt": "2010-03-12",
    "hasIndication": "false",
    "hasCorrection": "true",
    "chapitre": "Calcul d'intégrales",
    "sousChapitre": "Intégrale impropre",
    "organisation": "exo7",
    "updatedAt": "2025-03-04T15:12:41.343Z"
  },
  "contenu": [
    {
      "id": "145fe20d-3a2e-4cae-a97c-76179dc76ab1",
      "type": "description",
      "value": {
        "latex": "On pose $f(x) =  \\int_{t=x}^{+\\infty} \\frac{e^{-t}}t \\,d t$.",
        "html": "<p>On pose <span class=\"math inline\">\\(f(x) =  \\int_{t=x}^{+\\infty}\n\\frac{e^{-t}}t \\,d t\\)</span>.</p>\n"
      }
    },
    {
      "id": "c2eebefd-201c-43c3-9dc9-e6890b5266ee",
      "type": "question",
      "value": {
        "latex": "Chercher $\\lim_{x\\to{+\\infty}} f(x)$.",
        "html": "<p>Chercher <span class=\"math inline\">\\(\\lim_{x\\to{+\\infty}}\nf(x)\\)</span>.</p>\n"
      }
    },
    {
      "id": "f27fb1f9-e447-4605-9d33-920cd9b95855",
      "type": "question",
      "value": {
        "latex": "A l'aide d'une intégration par parties, donner un équivalent de $f(x)$\n      pour $x\\to{+\\infty}$.",
        "html": "<p>A l’aide d’une intégration par parties, donner un équivalent de <span\nclass=\"math inline\">\\(f(x)\\)</span> pour <span\nclass=\"math inline\">\\(x\\to{+\\infty}\\)</span>.</p>\n"
      }
    },
    {
      "id": "31ff2f8b-c70d-4b79-a37e-afd51a19055a",
      "type": "question",
      "value": {
        "latex": "Donner un équivalent de $f(x)$ pour $x\\to0^+$.",
        "html": "<p>Donner un équivalent de <span class=\"math inline\">\\(f(x)\\)</span>\npour <span class=\"math inline\">\\(x\\to0^+\\)</span>.</p>\n"
      }
    },
    {
      "id": "f29f656d-e1ad-4cd5-8c52-acc956ed9286",
      "type": "reponse",
      "value": {
        "latex": "$e^{-x}/x$.\n$-\\ln x$.",
        "html": "<p><span class=\"math inline\">\\(e^{-x}/x\\)</span>. <span\nclass=\"math inline\">\\(-\\ln x\\)</span>.</p>\n"
      }
    }
  ],
  "preview": "<p>On pose <span class=\"math inline\">\\(f(x) =  \\int_{t=x}^{+\\infty}\n\\frac{e^{-t}}t \\,d t\\)</span>.</p>\n"
}