{
  "uuid": "r1Th",
  "titre": "",
  "theme": "",
  "niveau": "",
  "metadata": {
    "exo7id": "3988",
    "auteur": "quercia",
    "createdAt": "2010-03-11",
    "hasIndication": "false",
    "hasCorrection": "true",
    "chapitre": "Dérivabilité des fonctions réelles",
    "sousChapitre": "Fonctions convexes",
    "organisation": "exo7",
    "updatedAt": "2025-02-13T07:42:19.536Z"
  },
  "contenu": [
    {
      "id": "c5d66cfb-b2bf-4756-a665-d28e1270f1b4",
      "type": "description",
      "value": {
        "latex": "Soit $f : \\R \\to \\R$ deux fois dérivable telle que :\n$f \\ge 0$, $f' \\ge 0$, $f'' \\ge 0$.",
        "html": "<p>Soit <span class=\"math inline\">\\(f : \\R \\to \\R\\)</span> deux fois dérivable telle que : <span class=\"math inline\">\\(f \\ge 0\\)</span>, <span class=\"math inline\">\\(f&#39; \\ge 0\\)</span>, <span class=\"math inline\">\\(f&#39;&#39; \\ge 0\\)</span>.</p>\n"
      }
    },
    {
      "id": "fdb1d158-b356-4722-bfe5-b62591f54b83",
      "type": "question",
      "value": {
        "latex": "\\'Etudier l'existence des limites (dans $\\overline\\R\\,$)\n    en $+\\infty$ de $f(x)$, $f'(x)$, $\\frac {f(x)}x$.",
        "html": "<p>Étudier l’existence des limites (dans <span class=\"math inline\">\\(\\overline\\R\\,\\)</span>) en <span class=\"math inline\">\\(+\\infty\\)</span> de <span class=\"math inline\">\\(f(x)\\)</span>, <span class=\"math inline\">\\(f&#39;(x)\\)</span>, <span class=\"math inline\">\\(\\frac {f(x)}x\\)</span>.</p>\n"
      }
    },
    {
      "id": "de77adf5-f8a0-4493-b9cd-c4b7bea5ca63",
      "type": "question",
      "value": {
        "latex": "Même question pour les limites en $-\\infty$ de $f(x)$, $f'(x)$, et $xf'(x)$.",
        "html": "<p>Même question pour les limites en <span class=\"math inline\">\\(-\\infty\\)</span> de <span class=\"math inline\">\\(f(x)\\)</span>, <span class=\"math inline\">\\(f&#39;(x)\\)</span>, et <span class=\"math inline\">\\(xf&#39;(x)\\)</span>.</p>\n"
      }
    },
    {
      "id": "1fbf6317-4207-450b-910f-b052f252773b",
      "type": "reponse",
      "value": {
        "latex": "$f(x) \\to \\ell \\in\\R$,\\quad\n             $f'(x) \\to 0$.\\par\n             TAF entre $x$ et $x/2$ $ \\Rightarrow  2\\left(f(x) - f\\left(\\frac x2\\right)\\right) \\le xf'(x) \\le 0\n              \\Rightarrow  xf'(x) \\to 0$.",
        "html": "<p><span class=\"math inline\">\\(f(x) \\to \\ell \\in\\R\\)</span>, <span class=\"math inline\">\\(f&#39;(x) \\to 0\\)</span>.</p>\n<p>TAF entre <span class=\"math inline\">\\(x\\)</span> et <span class=\"math inline\">\\(x/2\\)</span> <span class=\"math inline\">\\(\\Rightarrow  2\\left(f(x) - f\\left(\\frac x2\\right)\\right) \\le xf&#39;(x) \\le 0\n              \\Rightarrow  xf&#39;(x) \\to 0\\)</span>.</p>\n"
      }
    }
  ],
  "preview": "<p>Soit <span class=\"math inline\">\\(f : \\R \\to \\R\\)</span> deux fois dérivable telle que : <span class=\"math inline\">\\(f \\ge 0\\)</span>, <span class=\" ..."
}