{
  "uuid": "ovvg",
  "titre": "",
  "theme": "",
  "niveau": "",
  "metadata": {
    "exo7id": "4661",
    "auteur": "quercia",
    "createdAt": "2010-03-14",
    "hasIndication": "false",
    "hasCorrection": "true",
    "chapitre": "Série de Fourier",
    "sousChapitre": "Autre",
    "organisation": "exo7",
    "updatedAt": "2025-02-13T07:45:26.934Z"
  },
  "contenu": [
    {
      "id": "91b3565e-abb1-49f2-9ec6-89239a850dfc",
      "type": "description",
      "value": {
        "latex": "Soit $k \\in \\R$.\nRésoudre l'équation différentielle $y'' + k^2y = \\sum_{n=1}^\\infty \\frac{\\cos nx}{n^2}$.",
        "html": "<p>Soit <span class=\"math inline\">\\(k \\in \\R\\)</span>. Résoudre l’équation différentielle <span class=\"math inline\">\\(y&#39;&#39; + k^2y = \\sum_{n=1}^\\infty \\frac{\\cos nx}{n^2}\\)</span>.</p>\n"
      }
    },
    {
      "id": "d816a5e8-d4ad-4f4a-ab75-2a4a7da4e359",
      "type": "reponse",
      "value": {
        "latex": "$k \\notin\\Z$ : $y = \\sum_{k=1}^\\infty \\frac{\\cos nx}{n^2(k^2-n^2)}\n                        + a\\cos kx + b\\sin kx$.\\par\n         $k\\in\\Z$ : remplacer $\\frac{\\cos kx}{k^2(k^2-k^2)}$ par\n                        $\\frac{x\\cos kx}{2k^3}$.",
        "html": "<p><span class=\"math inline\">\\(k \\notin\\Z\\)</span> : <span class=\"math inline\">\\(y = \\sum_{k=1}^\\infty \\frac{\\cos nx}{n^2(k^2-n^2)}\n                        + a\\cos kx + b\\sin kx\\)</span>.</p>\n<p><span class=\"math inline\">\\(k\\in\\Z\\)</span> : remplacer <span class=\"math inline\">\\(\\frac{\\cos kx}{k^2(k^2-k^2)}\\)</span> par <span class=\"math inline\">\\(\\frac{x\\cos kx}{2k^3}\\)</span>.</p>\n"
      }
    }
  ],
  "preview": "<p>Soit <span class=\"math inline\">\\(k \\in \\R\\)</span>. Résoudre l’équation différentielle <span class=\"math inline\"> ..."
}