{
  "uuid": "Zrjg",
  "titre": "",
  "theme": "",
  "niveau": "",
  "metadata": {
    "exo7id": "4613",
    "auteur": "quercia",
    "createdAt": "2010-03-14",
    "hasIndication": "false",
    "hasCorrection": "false",
    "chapitre": "Série entière",
    "sousChapitre": "Analycité",
    "organisation": "exo7",
    "updatedAt": "2025-03-04T15:18:30.139Z"
  },
  "contenu": [
    {
      "id": "cabaee8e-9f8a-44f7-a4cb-080f06d016ea",
      "type": "description",
      "value": {
        "latex": "Soit $f(z) = \\sum a_nz^n$ une série de rayon $R>0$ telle que\npour tout $z\\in \\mathring D(0,R)$ on a $f(z)\\in\\R$.\nMontrer que $f$ est constante.",
        "html": "<p>Soit <span class=\"math inline\">\\(f(z) = \\sum a_nz^n\\)</span> une\nsérie de rayon <span class=\"math inline\">\\(R&gt;0\\)</span> telle que\npour tout <span class=\"math inline\">\\(z\\in \\mathring D(0,R)\\)</span> on\na <span class=\"math inline\">\\(f(z)\\in\\R\\)</span>. Montrer que <span\nclass=\"math inline\">\\(f\\)</span> est constante.</p>\n"
      }
    }
  ],
  "preview": "<p>Soit <span class=\"math inline\">\\(f(z) = \\sum a_nz^n\\)</span> une\nsérie de rayon <span class=\"math inline\">\\(R&gt;0\\)</span> telle que\npour tout <sp ..."
}