{
  "uuid": "HVWQ",
  "titre": "",
  "theme": "",
  "niveau": "",
  "metadata": {
    "exo7id": "2743",
    "auteur": "tumpach",
    "createdAt": "2009-10-25",
    "hasIndication": "false",
    "hasCorrection": "false",
    "chapitre": "Application linéaire",
    "sousChapitre": "Image et noyau, théorème du rang",
    "organisation": "exo7",
    "updatedAt": "2025-03-04T15:09:44.829Z"
  },
  "contenu": [
    {
      "id": "b2ce3cf2-3c0f-4c7a-a79e-50fa76cb6919",
      "type": "description",
      "value": {
        "latex": "",
        "html": "\n"
      }
    },
    {
      "id": "3e6a7df8-bf56-4513-bc8d-5b3ef0914404",
      "type": "question",
      "value": {
        "latex": "Soit $f$ une application lin\\'eaire surjective de $\\mathbb{R}^{4}$ dans $\\mathbb{R}^2$.  Quelle est la dimension du noyau de $f$~?",
        "html": "<p>Soit <span class=\"math inline\">\\(f\\)</span> une application linéaire\nsurjective de <span class=\"math inline\">\\(\\mathbb{R}^{4}\\)</span> dans\n<span class=\"math inline\">\\(\\mathbb{R}^2\\)</span>. Quelle est la\ndimension du noyau de <span class=\"math inline\">\\(f\\)</span> ?</p>\n"
      }
    },
    {
      "id": "a71bb04f-50e9-4d5a-a0d8-cb2d1da218f6",
      "type": "question",
      "value": {
        "latex": "Soit $g$ une application injective de $\\mathbb{R}^{26}$ dans $\\mathbb{R}^{100}$. Quelle est la dimension de l'image de $g$~?",
        "html": "<p>Soit <span class=\"math inline\">\\(g\\)</span> une application injective\nde <span class=\"math inline\">\\(\\mathbb{R}^{26}\\)</span> dans <span\nclass=\"math inline\">\\(\\mathbb{R}^{100}\\)</span>. Quelle est la dimension\nde l’image de <span class=\"math inline\">\\(g\\)</span> ?</p>\n"
      }
    },
    {
      "id": "9a3edd27-7c0c-46f4-b80a-95dbdb67e588",
      "type": "question",
      "value": {
        "latex": "Existe-t-il une application lin\\'eaire bijective entre $\\mathbb{R}^{50}$ et $\\mathbb{R}^{72}$~?",
        "html": "<p>Existe-t-il une application linéaire bijective entre <span\nclass=\"math inline\">\\(\\mathbb{R}^{50}\\)</span> et <span\nclass=\"math inline\">\\(\\mathbb{R}^{72}\\)</span> ?</p>\n"
      }
    }
  ],
  "preview": "<p>Soit <span class=\"math inline\">\\(f\\)</span> une application linéaire\nsurjective de <span class=\"math inline\">\\(\\mathbb{R}^{4}\\)</span> dans\n<span c ..."
}