{
  "uuid": "vcqM",
  "titre": "",
  "theme": "",
  "niveau": "",
  "metadata": {
    "exo7id": "3274",
    "auteur": "quercia",
    "createdAt": "2010-03-08",
    "hasIndication": "false",
    "hasCorrection": "true",
    "chapitre": "Polynôme, fraction rationnelle",
    "sousChapitre": "Fraction rationnelle",
    "organisation": "exo7",
    "updatedAt": "2025-02-13T07:38:47.263Z"
  },
  "contenu": [
    {
      "id": "71fe4d21-f4ed-4361-9869-83ad206e5f74",
      "type": "description",
      "value": {
        "latex": "",
        "html": "\n"
      }
    },
    {
      "id": "b7ea5746-3a9c-4642-aae7-d45901a61dc6",
      "type": "question",
      "value": {
        "latex": "Soit $F \\in {\\C(X)}$ telle que $F(e^{2i\\pi/n}X) = F(X)$.\n    Montrer qu'il existe une unique fraction $G \\in {\\C(X)}$ telle que $F(X) = G(X^n)$.",
        "html": "<p>Soit <span class=\"math inline\">\\(F \\in {\\C(X)}\\)</span> telle que <span class=\"math inline\">\\(F(e^{2i\\pi/n}X) = F(X)\\)</span>. Montrer qu’il existe une unique fraction <span class=\"math inline\">\\(G \\in {\\C(X)}\\)</span> telle que <span class=\"math inline\">\\(F(X) = G(X^n)\\)</span>.</p>\n"
      }
    },
    {
      "id": "91fc72cf-3106-4e5d-b793-29aed90ade63",
      "type": "question",
      "value": {
        "latex": "Application : Simplifier\n    $\\sum_{k=0}^{n-1} \\frac {X+e^{2ik\\pi/n}}{X-e^{2ik\\pi/n}}$.",
        "html": "<p>Application : Simplifier <span class=\"math inline\">\\(\\sum_{k=0}^{n-1} \\frac {X+e^{2ik\\pi/n}}{X-e^{2ik\\pi/n}}\\)</span>.</p>\n"
      }
    },
    {
      "id": "d7cfc5eb-c12e-49c3-ad2c-4307d5bfa529",
      "type": "reponse",
      "value": {
        "latex": "$n\\frac {X^n+1}{X^n-1}$.",
        "html": "<p><span class=\"math inline\">\\(n\\frac {X^n+1}{X^n-1}\\)</span>.</p>\n"
      }
    }
  ],
  "preview": "<p>Soit <span class=\"math inline\">\\(F \\in {\\C(X)}\\)</span> telle que <span class=\"math inline\">\\(F(e^{2i\\pi/n}X) = F(X)\\)</span>. Montrer qu’il existe ..."
}