{
  "uuid": "X6EZ",
  "titre": "",
  "theme": "",
  "niveau": "",
  "metadata": {
    "exo7id": "291",
    "auteur": "bodin",
    "createdAt": "1998-09-01",
    "hasIndication": "false",
    "hasCorrection": "false",
    "chapitre": "Arithmétique dans Z",
    "sousChapitre": "Pgcd, ppcm, algorithme d'Euclide",
    "organisation": "exo7",
    "updatedAt": "2025-03-04T15:10:21.485Z"
  },
  "contenu": [
    {
      "id": "f92ecfb2-19f0-4c37-a0a5-df5f6cee0a81",
      "type": "description",
      "value": {
        "latex": "",
        "html": "\n"
      }
    },
    {
      "id": "4f4cf892-9982-4a49-a2dd-73067d444dd5",
      "type": "question",
      "value": {
        "latex": "Calculer le ppcm des nombres  : 108 et 144 ; 128 et 230 ; 6, 16 et 50.",
        "html": "<p>Calculer le ppcm des nombres : 108 et 144 ; 128 et 230 ; 6, 16 et\n50.</p>\n"
      }
    },
    {
      "id": "1a9dde28-8edd-4df1-972d-186774895c6b",
      "type": "question",
      "value": {
        "latex": "Montrer que si $a\\ge 1$ et $b\\ge 1$ sont des entiers\n    de pgcd $d$ et, si on pose $a=da' ; b=db' $, le ppcm de $a$ et $b$ est $da'b'$.",
        "html": "<p>Montrer que si <span class=\"math inline\">\\(a\\ge 1\\)</span> et <span\nclass=\"math inline\">\\(b\\ge 1\\)</span> sont des entiers de pgcd <span\nclass=\"math inline\">\\(d\\)</span> et, si on pose <span\nclass=\"math inline\">\\(a=da&#39; ; b=db&#39;\\)</span>, le ppcm de <span\nclass=\"math inline\">\\(a\\)</span> et <span\nclass=\"math inline\">\\(b\\)</span> est <span\nclass=\"math inline\">\\(da&#39;b&#39;\\)</span>.</p>\n"
      }
    },
    {
      "id": "83f01026-d59d-49b2-8755-6df8d9469a7f",
      "type": "question",
      "value": {
        "latex": "Montrer que si $a,b,c$ sont des entiers sup\\'erieurs \\`a  $1$,\n    on a :\n    $$\\text{ppcm}(a,b,c)=\\text{ppcm}(\\text{ppcm}(a,b),c).$$",
        "html": "<p>Montrer que si <span class=\"math inline\">\\(a,b,c\\)</span> sont des\nentiers supérieurs à <span class=\"math inline\">\\(1\\)</span>, on a :\n<span\nclass=\"math display\">\\[\\text{ppcm}(a,b,c)=\\text{ppcm}(\\text{ppcm}(a,b),c).\\]</span></p>\n"
      }
    }
  ],
  "preview": "<p>Calculer le ppcm des nombres : 108 et 144 ; 128 et 230 ; 6, 16 et\n50.</p>\n"
}