{
  "uuid": "YEmN",
  "titre": "",
  "theme": "",
  "niveau": "",
  "metadata": {
    "exo7id": "3140",
    "auteur": "quercia",
    "createdAt": "2010-03-08",
    "hasIndication": "false",
    "hasCorrection": "true",
    "chapitre": "Arithmétique dans Z",
    "sousChapitre": "Nombres premiers, nombres premiers entre eux",
    "organisation": "exo7",
    "updatedAt": "2025-02-13T07:38:06.702Z"
  },
  "contenu": [
    {
      "id": "f859fe73-8c3f-4b86-ae11-759f48eb4552",
      "type": "description",
      "value": {
        "latex": "On rappelle que si $p$ est premier et $n\\wedge p = 1$, alors\n$n^{p-1} \\equiv 1(\\mathrm{mod}\\, p)$.",
        "html": "<p>On rappelle que si <span class=\"math inline\">\\(p\\)</span> est premier et <span class=\"math inline\">\\(n\\wedge p = 1\\)</span>, alors <span class=\"math inline\">\\(n^{p-1} \\equiv 1(\\mathrm{mod}\\, p)\\)</span>.</p>\n"
      }
    },
    {
      "id": "d1113805-b779-4178-a706-3d378b4aed2f",
      "type": "question",
      "value": {
        "latex": "Soit $n\\in \\N$ et $p\\ge 3$ un diviseur premier de $n^2+1$.\n    Montrer que $p\\equiv 1(\\mathrm{mod}\\, 4)$.",
        "html": "<p>Soit <span class=\"math inline\">\\(n\\in \\N\\)</span> et <span class=\"math inline\">\\(p\\ge 3\\)</span> un diviseur premier de <span class=\"math inline\">\\(n^2+1\\)</span>. Montrer que <span class=\"math inline\">\\(p\\equiv 1(\\mathrm{mod}\\, 4)\\)</span>.</p>\n"
      }
    },
    {
      "id": "2982aa18-1d81-4137-b91a-aa05873d28cf",
      "type": "question",
      "value": {
        "latex": "En d{\\'e}duire qu'il y a une infinit{\\'e} de nombres premiers de la forme $4k+1$.",
        "html": "<p>En d<span>é</span>duire qu’il y a une infinit<span>é</span> de nombres premiers de la forme <span class=\"math inline\">\\(4k+1\\)</span>.</p>\n"
      }
    },
    {
      "id": "ae3098ae-6c06-4fb5-9a17-ca1bd584a52e",
      "type": "reponse",
      "value": {
        "latex": "$(-1)^{(p-1)/2}\\equiv 1(\\mathrm{mod}\\, p)$.",
        "html": "<p><span class=\"math inline\">\\((-1)^{(p-1)/2}\\equiv 1(\\mathrm{mod}\\, p)\\)</span>.</p>\n"
      }
    }
  ],
  "preview": "<p>On rappelle que si <span class=\"math inline\">\\(p\\)</span> est premier et <span class=\"math inline\">\\(n\\wedge p = 1\\)</span>, alors <span class=\"mat ..."
}