{
  "uuid": "Updx",
  "titre": "",
  "theme": "",
  "niveau": "",
  "metadata": {
    "exo7id": "4895",
    "auteur": "quercia",
    "createdAt": "2010-03-17",
    "hasIndication": "false",
    "hasCorrection": "true",
    "chapitre": "Géométrie affine dans le plan et dans l'espace",
    "sousChapitre": "Propriétés des triangles",
    "organisation": "exo7",
    "updatedAt": "2025-03-04T15:27:54.153Z"
  },
  "contenu": [
    {
      "id": "2066b1b4-f4be-4a0d-ae5b-d99bef9a7d33",
      "type": "description",
      "value": {
        "latex": "Soient $A,B,C$ trois points non alignés et $M_1 \\in (AB)$.\nOn construit les points $M_2,M_3,M_4$ de la manière suivante~:\n\n-- $M_2$ est le projeté de $M_1$ sur $(BC)$ parallèlement à $(AC)$.\\par\n-- $M_3$ est le projeté de $M_2$ sur $(AC)$ parallèlement à $(AB)$.\\par\n-- $M_4$ est le projeté de $M_3$ sur $(AB)$ parallèlement à $(BC)$.\\par\n\nOn recommence ensuite les mêmes constructions à partir de $M_4$, ce qui\ndonne les points $M_5, M_6, M_7$.\n\nMontrer que $M_7 = M_1$.",
        "html": "<p>Soient <span class=\"math inline\">\\(A,B,C\\)</span> trois points non\nalignés et <span class=\"math inline\">\\(M_1 \\in (AB)\\)</span>. On\nconstruit les points <span class=\"math inline\">\\(M_2,M_3,M_4\\)</span> de\nla manière suivante :</p>\n<p>– <span class=\"math inline\">\\(M_2\\)</span> est le projeté de <span\nclass=\"math inline\">\\(M_1\\)</span> sur <span\nclass=\"math inline\">\\((BC)\\)</span> parallèlement à <span\nclass=\"math inline\">\\((AC)\\)</span>.</p>\n<p>– <span class=\"math inline\">\\(M_3\\)</span> est le projeté de <span\nclass=\"math inline\">\\(M_2\\)</span> sur <span\nclass=\"math inline\">\\((AC)\\)</span> parallèlement à <span\nclass=\"math inline\">\\((AB)\\)</span>.</p>\n<p>– <span class=\"math inline\">\\(M_4\\)</span> est le projeté de <span\nclass=\"math inline\">\\(M_3\\)</span> sur <span\nclass=\"math inline\">\\((AB)\\)</span> parallèlement à <span\nclass=\"math inline\">\\((BC)\\)</span>.</p>\n<p>On recommence ensuite les mêmes constructions à partir de <span\nclass=\"math inline\">\\(M_4\\)</span>, ce qui donne les points <span\nclass=\"math inline\">\\(M_5, M_6, M_7\\)</span>.</p>\n<p>Montrer que <span class=\"math inline\">\\(M_7 = M_1\\)</span>.</p>\n"
      }
    },
    {
      "id": "5c598951-ab9a-4a12-b612-0be3c60a4079",
      "type": "reponse",
      "value": {
        "latex": "$M_1 \\mapsto M_4$ est affine, et échange $A$ et $B$. $\\Rightarrow$ involutive.",
        "html": "<p><span class=\"math inline\">\\(M_1 \\mapsto M_4\\)</span> est affine, et\néchange <span class=\"math inline\">\\(A\\)</span> et <span\nclass=\"math inline\">\\(B\\)</span>. <span\nclass=\"math inline\">\\(\\Rightarrow\\)</span> involutive.</p>\n"
      }
    }
  ],
  "preview": "<p>Soient <span class=\"math inline\">\\(A,B,C\\)</span> trois points non\nalignés et <span class=\"math inline\">\\(M_1 \\in (AB)\\)</span>. On\nconstruit les p ..."
}