{
  "uuid": "GnVW",
  "titre": "",
  "theme": "",
  "niveau": "",
  "metadata": {
    "exo7id": "1736",
    "auteur": "gourio",
    "createdAt": "2001-09-01",
    "hasIndication": "false",
    "hasCorrection": "false",
    "chapitre": "Fonction convexe",
    "sousChapitre": "Fonction convexe",
    "organisation": "",
    "updatedAt": "2025-02-10T15:41:14.931Z"
  },
  "contenu": [
    {
      "id": "4d7de4da-ea5e-46ea-8cd4-520f5af4fba9",
      "type": "description",
      "value": {
        "latex": "Montrer que :\n$$\\forall n\\in \\Nn^{*},\\forall (x_{1},...,x_{n})\\in \\left( {\\Rr}^{+*}\\right)^{n},\n1+\\left( \\prod\\limits_{k=1}^{n}x_{k}\\right) ^{\\frac{1}{n}}\\leq\n\\left( 1+\\prod\\limits_{k=1}^{n}x_{k}\\right) ^{\\frac{1}{n}}. $$",
        "html": "<p>Montrer que : <span class=\"math display\">\\[\\forall n\\in \\Nn^{*},\\forall (x_{1},...,x_{n})\\in \\left( {\\Rr}^{+*}\\right)^{n},\n1+\\left( \\prod\\limits_{k=1}^{n}x_{k}\\right) ^{\\frac{1}{n}}\\leq\n\\left( 1+\\prod\\limits_{k=1}^{n}x_{k}\\right) ^{\\frac{1}{n}}.\\]</span></p>\n"
      }
    }
  ]
}